pyriskmgmt/SupportFunctions.py
pyriskmgmt/__init__.py
pyriskmgmt/derivative_models.py
pyriskmgmt/equity_models.py
pyriskmgmt/fixed_income_models.py
pyriskmgmt/inputsControlFunctions.py
pyriskmgmt-1.1.2.dist-info/METADATA
pyriskmgmt-1.1.2.dist-info/WHEEL
pyriskmgmt-1.1.2.dist-info/top_level.txt
pyriskmgmt-1.1.2.dist-info/RECORD
