Metadata-Version: 2.1
Name: pyriskmgmt
Version: 1.1.2
Summary: The pyriskmgmt package is designed to offer a straightforward but comprehensive platform for risk assessment, targeting the calculation of Value at Risk (VaR) and Expected Shortfall (ES) across various financial instruments. While providing a solid foundation, the package also allows for more specialized development to meet users' specific investment strategies and risk requirements.
Home-page: https://github.com/GianMarcoOddo/pyriskmgmt
Author: Gian Marco Oddo
Author-email: gian.marco.oddo@usi.ch
License: MIT
Requires-Dist: yfinance
Requires-Dist: numpy
Requires-Dist: pandas
Requires-Dist: scipy
Requires-Dist: rpy2
Requires-Dist: requests
Requires-Dist: QuantLib
Requires-Dist: arch
Requires-Dist: joblib
Requires-Dist: bs4
Requires-Dist: seaborn
Requires-Dist: matplotlib
